fmlpy/__init__.py
fmlpy/model/__init__.py
fmlpy/model/cross_val.py
fmlpy/model/seq_bootstrap.py
fmlpy/preprocess/__init__.py
fmlpy/preprocess/bars.py
fmlpy/preprocess/feature_mat.py
fmlpy/preprocess/filters.py
fmlpy/preprocess/frac_diff.py
fmlpy-0.1.1.dist-info/METADATA
fmlpy-0.1.1.dist-info/RECORD
fmlpy-0.1.1.dist-info/WHEEL
fmlpy-0.1.1.dist-info/top_level.txt
